cfgengine/__init__.py
cfgengine/config_loader.py
cfgengine/default_parser.py
cfgengine/parser.py
cfgengine-2.0.0.dist-info/LICENSE
cfgengine-2.0.0.dist-info/METADATA
cfgengine-2.0.0.dist-info/WHEEL
cfgengine-2.0.0.dist-info/top_level.txt
cfgengine-2.0.0.dist-info/RECORD
