Metadata-Version: 2.2
Name: cfgengine
Version: 2.0.0
Summary: A simple Python library to manage and load configuration files
Author-email: zjd-melo <zhujiadong.melo@gmail.com>
License: MIT License
Project-URL: Homepage, https://github.com/zjd-melo/cfgengine
Project-URL: Repository, https://github.com/zjd-melo/cfgengine.git
Project-URL: Issues, https://github.com/zjd-melo/cfgengine/issues
Keywords: config
Classifier: Programming Language :: Python :: 3
Classifier: License :: OSI Approved :: MIT License
Classifier: Operating System :: OS Independent
License-File: LICENSE
Requires-Dist: jinja2>=3.0.0
